mcmaxenttest/__init__.py
mcmaxenttest/mcmaxenttest.py
mcmaxenttest-1.0.data/scripts/demo_mcmaxenttest
mcmaxenttest-1.0.dist-info/DESCRIPTION.rst
mcmaxenttest-1.0.dist-info/METADATA
mcmaxenttest-1.0.dist-info/RECORD
mcmaxenttest-1.0.dist-info/WHEEL
mcmaxenttest-1.0.dist-info/metadata.json
mcmaxenttest-1.0.dist-info/top_level.txt
