Metadata-Version: 2.0
Name: mcmaxenttest
Version: 1.0
Summary: Statistical test to detect higher-order correlations between count variables.
Home-page: https://github.com/asnelt/mcmaxenttest/
Author: Arno Onken
Author-email: asnelt@asnelt.org
License: GPLv3+
Keywords: monte carlo poisson test maximum entropy correlation
Platform: UNKNOWN
Classifier: Development Status :: 5 - Production/Stable
Classifier: Intended Audience :: Science/Research
Classifier: License :: OSI Approved :: GNU General Public License v3 or later (GPLv3+)
Classifier: Operating System :: OS Independent
Classifier: Programming Language :: Python
Classifier: Topic :: Scientific/Engineering
Requires-Dist: scipy
